trainify/__init__.py
trainify/__main__.py
trainify/_version.py
trainify/train.py
trainify/configs/__init__.py
trainify/configs/config_metaclass.py
trainify/configs/default_components.py
trainify/configs/system_config.py
trainify/preparators/__init__.py
trainify/preparators/base_preparator.py
trainify/preparators/map_preparator.py
trainify/preparators/atomic/__init__.py
trainify/preparators/atomic/adder.py
trainify/preparators/atomic/cacher.py
trainify/preparators/atomic/dropper.py
trainify/preparators/atomic/filterer.py
trainify/preparators/atomic/loader.py
trainify/preparators/atomic/padder.py
trainify/preparators/atomic/remover.py
trainify/preparators/atomic/renamer.py
trainify/system/__init__.py
trainify/system/builder.py
trainify/system/callbackers/__init__.py
trainify/system/callbackers/accuracy_callbacker.py
trainify/system/callbackers/aux_callbacker.py
trainify/system/callbackers/base_callbacker.py
trainify/system/callbackers/loss_callbacker.py
trainify/system/callbackers/model_callbacker.py
trainify/system/trainers/__init__.py
trainify/system/trainers/base_trainer.py
trainify/system/trainers/parallel_train_wrapper.py
trainify/system/trainers/single_validation_trainer.py
trainify/system/trainers/trainer.py
trainify/system/utils/__init__.py
trainify/system/utils/averagers.py
trainify/system/utils/builder_utils.py
trainify/system/utils/callbacker_module.py
trainify/system/utils/checkpointer.py
trainify/system/utils/dataloaders.py
trainify/system/utils/samplers.py
trainify-0.0.1.dist-info/LICENSE
trainify-0.0.1.dist-info/METADATA
trainify-0.0.1.dist-info/WHEEL
trainify-0.0.1.dist-info/top_level.txt
trainify-0.0.1.dist-info/RECORD
